irods_capability_automated_ingest/__init__.py
irods_capability_automated_ingest/celery.py
irods_capability_automated_ingest/char_map_util.py
irods_capability_automated_ingest/core.py
irods_capability_automated_ingest/custom_event_handler.py
irods_capability_automated_ingest/evhdlr.py
irods_capability_automated_ingest/flask_app.py
irods_capability_automated_ingest/irods_sync.py
irods_capability_automated_ingest/irods_worker.py
irods_capability_automated_ingest/phl.py
irods_capability_automated_ingest/redis_key.py
irods_capability_automated_ingest/redis_utils.py
irods_capability_automated_ingest/scanner.py
irods_capability_automated_ingest/sync_actions.py
irods_capability_automated_ingest/sync_irods.py
irods_capability_automated_ingest/sync_job.py
irods_capability_automated_ingest/sync_logging.py
irods_capability_automated_ingest/sync_task.py
irods_capability_automated_ingest/sync_utils.py
irods_capability_automated_ingest/task_queue.py
irods_capability_automated_ingest/utils.py
irods_capability_automated_ingest/version.py
irods_capability_automated_ingest/examples/__init__.py
irods_capability_automated_ingest/examples/append.py
irods_capability_automated_ingest/examples/append_json.py
irods_capability_automated_ingest/examples/append_non_leaf_non_root_with_resc_name.py
irods_capability_automated_ingest/examples/append_root_with_resc_name.py
irods_capability_automated_ingest/examples/append_with_resc_name.py
irods_capability_automated_ingest/examples/coll_create_pre_and_post.py
irods_capability_automated_ingest/examples/coll_modify_pre_and_post.py
irods_capability_automated_ingest/examples/data_obj_create_pre_and_post.py
irods_capability_automated_ingest/examples/data_obj_modify_pre_and_post.py
irods_capability_automated_ingest/examples/metadata.py
irods_capability_automated_ingest/examples/no_op.py
irods_capability_automated_ingest/examples/no_retry.py
irods_capability_automated_ingest/examples/post_job.py
irods_capability_automated_ingest/examples/pre_job.py
irods_capability_automated_ingest-0.6.0.dist-info/AUTHORS
irods_capability_automated_ingest-0.6.0.dist-info/LICENSE.txt
irods_capability_automated_ingest-0.6.0.dist-info/METADATA
irods_capability_automated_ingest-0.6.0.dist-info/WHEEL
irods_capability_automated_ingest-0.6.0.dist-info/entry_points.txt
irods_capability_automated_ingest-0.6.0.dist-info/top_level.txt
irods_capability_automated_ingest-0.6.0.dist-info/RECORD
