Metadata-Version: 2.1
Name: irods-capability-automated-ingest
Version: 0.6.0
Summary: Implement filesystem scanners and landing zones
Home-page: https://github.com/irods/irods_capability_automated_ingest
Author: iRODS Consortium
Author-email: support@irods.org
License: BSD
Project-URL: Bug Reports, https://github.com/irods/irods_capability_automated_ingest/issues
Project-URL: Source, https://github.com/irods/irods_capability_automated_ingest
Keywords: irods automated ingest landingzone filesystem
Platform: UNKNOWN
Classifier: Development Status :: 4 - Beta
Classifier: License :: OSI Approved :: BSD License
Classifier: Natural Language :: English
Classifier: Operating System :: POSIX :: Linux
Classifier: Programming Language :: Python
Classifier: Programming Language :: Python :: 3 :: Only
Classifier: Programming Language :: Python :: 3
Classifier: Programming Language :: Python :: 3.8
Classifier: Programming Language :: Python :: 3.9
Classifier: Programming Language :: Python :: 3.10
Classifier: Programming Language :: Python :: 3.11
Classifier: Programming Language :: Python :: 3.12
Requires-Python: >=3.8,
Requires-Dist: celery[redis] (<6.0.0)
Requires-Dist: minio
Requires-Dist: progressbar2
Requires-Dist: python-irodsclient (<3.0.0)
Requires-Dist: python-redis-lock (>=3.2.0)
Requires-Dist: redis (<5.0.0,>=3.4.1)
Requires-Dist: scandir
Requires-Dist: structlog (>=18.1.0)
